lektor_responsive_image-1.0.0.dist-info/METADATA
lektor_responsive_image-1.0.0.dist-info/WHEEL
lektor_responsive_image-1.0.0.dist-info/entry_points.txt
lektor_responsive_image-1.0.0.dist-info/licenses/LICENSE
lektor_responsive_image.py
lektor_responsive_image-1.0.0.dist-info/RECORD
