Metadata-Version: 2.1
Name: lektor-responsive-image
Version: 1.0.0
Summary: Lektor plugin to help with multi-resolution responsive images
Keywords: Lektor plugin responsive images multi-resolution images srcset
Author-Email: Jeff Dairiki <dairiki@dairiki.org>
License: Copyright © 2021 Geoffrey T. Dairiki
Classifier: Development Status :: 5 - Production/Stable
Classifier: Environment :: Plugins
Classifier: Environment :: Web Environment
Classifier: Framework :: Lektor
Classifier: Intended Audience :: Developers
Classifier: License :: OSI Approved :: MIT License
Classifier: Programming Language :: Python :: 3
Classifier: Programming Language :: Python :: 3.8
Classifier: Programming Language :: Python :: 3.9
Classifier: Programming Language :: Python :: 3.10
Classifier: Programming Language :: Python :: 3.11
Classifier: Programming Language :: Python :: 3.12
Classifier: Topic :: Text Processing :: Markup :: HTML
Project-URL: Home, https://github.com/dairiki/lektor-responsive-image
Requires-Python: >=3.8
